{
    "tree": {
        "name": "Tailored Datasets",
        "tree": [
            {
                "id": "td-1",
                "title": "Automation basics",
                "icon": "icons/RoundIcons_FreeSet-35.svg",
                "tooltip": {
                    "content": "Use of automation tool to fully extract data enquiries."
                },
                "children": [
                    {
                        "id": "td-2",
                        "title": "SQL beginner",
                        "icon": "icons/RoundIcons_FreeSet-35.svg",
                        "tooltip": {
                            "content": "Able to tweak scripts from the automation tool and add in bespoke fields."
                        },
                        "children": [
                            {
                                "id": "td-3",
                                "title": "Formats 1",
                                "icon": "icons/RoundIcons_FreeSet-35.svg",
                                "tooltip": {
                                    "content": "Extracting unusual format e.g. PowerBI, Tableau, DDS and spreadsheets."
                                },
                                "children": [
                                    {
                                        "id": "td-4",
                                        "title": "SQL scripts",
                                        "icon": "icons/RoundIcons_FreeSet-35.svg",
                                        "tooltip": {
                                            "content": "Able to write simple SQL scripts from scratch."
                                        },
                                        "children": [
                                            {
                                                "id": "td-5",
                                                "title": "Run the derived table",
                                                "icon": "icons/RoundIcons_FreeSet-35.svg",
                                                "tooltip": {
                                                    "content": "Able to pick up and run the derived tables script, and amend as needed."
                                                },
                                                "children": [
                                                    {
                                                        "id": "td-9",
                                                        "title": "More complex SQL",
                                                        "icon": "icons/RoundIcons_FreeSet-35.svg",
                                                        "tooltip": {
                                                            "content": "Complicated SQL (e.g. tracking and linking) with the support of Master colleagues."
                                                        },
                                                        "children": []
                                                    }
                                                ]
                                            }
                                        ]
                                    }
                                ]
                            }
                        ]
                    }
                ]
            },
            {
                "id": "td-6",
                "title": "Provider Preview",
                "icon": "icons/RoundIcons_FreeSet-33.svg",
                "tooltip": {
                    "content": "Able to put data enquiries on the provider preview system and answer simple/modest questions on the data enquiry."
                },
                "children": [
                    {
                        "id": "td-7",
                        "title": "Checking simple data enquiries",
                        "icon": "icons/RoundIcons_FreeSet-33.svg",
                        "tooltip": {
                            "content": "Checking pivot table and spreadsheet data enquiries."
                        },
                        "children": [
                            {
                                "id": "td-8",
                                "title": "Checking all formats",
                                "icon": "icons/RoundIcons_FreeSet-33.svg",
                                "tooltip": {
                                    "content": "Checking all formats of data enquiries."
                                },
                                "children": [
                                    {
                                        "id": "td-10",
                                        "title": "Checking more complex enquiries",
                                        "icon": "icons/RoundIcons_FreeSet-33.svg",
                                        "tooltip": {
                                            "content": "Fully able to check data enquiries of all levels of complexity e.g. PowerBI, Tableau."
                                        },
                                        "children": [
                                            {
                                                "id": "td-11",
                                                "title": "Checking the most complex enquiries",
                                                "icon": "icons/RoundIcons_FreeSet-33.svg",
                                                "tooltip": {
                                                    "content": "Checking tracking and linking enquiries."
                                                },
                                                "children": []
                                            }
                                        ]
                                    }
                                ]
                            }
                        ]
                    }
                ]
            },
            {
                "id": "tdt-1",
                "title": "Datatypes",
                "icon": "icons/RoundIcons_FreeSet-43.svg",
                "tooltip": {
                    "content": "Understanding datatypes and how they affect the scripts (e.g. char vs int)."
                },
                "children": [
                    {
                        "id": "tdt-2",
                        "title": "Debugging",
                        "icon": "icons/RoundIcons_FreeSet-43.svg",
                        "tooltip": {
                            "content": "Be able to Debug SQL scripts when an error appears, identify the problem and correct."
                        },
                        "children": [
                            {
                                "id": "tdt-3",
                                "title": "Automation tool maintenence",
                                "icon": "icons/RoundIcons_FreeSet-43.svg",
                                "tooltip": {
                                    "content": "Helping maintain/update the automation tool."
                                },
                                "children": [
                                    {
                                        "id": "tdt-4",
                                        "title": "Intermediate SQL knowledge",
                                        "icon": "icons/RoundIcons_FreeSet-43.svg",
                                        "tooltip": {
                                            "content": "Confident with SQL and writing scripts efficiently."
                                        },
                                        "children": [
                                            {
                                                "id": "tdt-5",
                                                "title": "Other useful tools",
                                                "icon": "icons/RoundIcons_FreeSet-43.svg",
                                                "tooltip": {
                                                    "content": "Able to use other software to facilitate efficiency gain in TDS e.g. Python/Alteryx."
                                                },
                                                "children": [
                                                    {
                                                        "id": "tdt-6",
                                                        "title": "Expert SQL knowledge",
                                                        "icon": "icons/RoundIcons_FreeSet-43.svg",
                                                        "tooltip": {
                                                            "content": "Expert with SQL e.g. indexes."
                                                        },
                                                        "children": []
                                                    }
                                                ]
                                            }
                                        ]
                                    }
                                ]
                            }
                        ]
                    }
                ]
            }
        ]
    }
}
